jcrs/__init__.py
jcrs/server.py
jcrs-1.0.dist-info/METADATA
jcrs-1.0.dist-info/WHEEL
jcrs-1.0.dist-info/entry_points.txt
jcrs-1.0.dist-info/top_level.txt
jcrs-1.0.dist-info/RECORD
