Metadata-Version: 2.1
Name: jcrs
Version: 1.0
Summary: JenCat TCP Relay Server
Home-page: UNKNOWN
Author: JenCat
Author-email: gubenkovalik@gmail.com
License: MIT
Keywords: tcp relay server
Platform: UNKNOWN
Classifier: Development Status :: 4 - Beta
Classifier: Intended Audience :: End Users/Desktop
Classifier: Topic :: Utilities
Classifier: License :: OSI Approved :: MIT License
Classifier: Programming Language :: Python :: 3
Requires-Python: >=3.8
